AP7 - CD/morse.v
/*
class Peca(ABC):
    x : int
    y : int

    def __init__(self):
        self.x = 0
        self.y = 0
    
    p1 = Azul()
*/

module morse (
    in, out, reset, clk
);
    input in, reset, clk;
    output reg [7:0] out;

    parameter IDLE = 5'bxxxxx, E = 5'b00000, A = 5'b00001, T = 5'b00010, I = 5'b00100, U = 5'b00110, S = 5'b00111, V = 5'b01110, H = 5'b01111;
    reg [5:0] state, next_state;

    // Lógica Sequencial    
    always @(posedge clk) begin
        if (reset)
            state = IDLE;
        else
            state = next_state;        
    end
    
    // Lógica Combinacional de entrada
    always @(*) begin
        case (state)   // 1 -> ponto 0 -> traço
            IDLE: begin
                if (in)
                    next_state = E; // .
                else
                    next_state = T; // -
            end   
            E: begin
                if (in)
                    next_state = I; // ..
                else
                    next_state = A; // .-
            end
            I: begin
                if(in)
                    next_state = S; // ...
                else
                    next_state = U; // ..-  
            end
            S: begin
                if(in)
                    next_state = H; // ....
                else
                    next_state = V; // ...-  
            end                                    
            default: next_state = IDLE;
        endcase
        
    end

    // Lógica Combinacional de saída
    always @(*) begin
        case (state)
            IDLE: out = 8'h00;
            E: out = 8'h45;
            T: out = 8'h54;
            A: out = 8'h41;
            I: out = 8'h49; 
            S: out = 8'h53;
            U: out = 8'h55;
            H: out = 8'h48;
            V: out = 8'h56;
            default: next_state = IDLE;
        endcase
    end
endmodule

AP7 - CD/morse_tb.v
`timescale 10ns/1ns
`include "morse.v"

module morse_tb;


    reg in, reset, clk;
    wire [7:0] out;
    morse uut(in, out, reset, clk);

    initial begin
        $dumpfile("morse.vcd");
        $dumpvars(0, morse_tb);

        // vai printar "SAUVE, fiquei c preguiça de fzr até o L"

        reset = 1; #15 reset = 0;
        in = 1; #60
        reset = 1; #45 reset = 0;
        in = 1; #20
        in = 0; #20
        reset = 1; #45 reset = 0;
        in = 1; #40
        in = 0; #20
        reset = 1; #45 reset = 0;
        in = 1; #60
        in = 0; #20
        reset = 1; #45 reset = 0;
        in = 1; #30

        $finish;
    end

    initial begin
        clk = 0;
        forever #10 clk = ~clk;
    end
    

endmodule

AP7 - CD/morse.vcd
$date
	Mon Nov 18 09:44:01 2024
$end
$version
	Icarus Verilog
$end
$timescale
	1ns
$end
$scope module morse_tb $end
$var wire 8 ! out [7:0] $end
$var reg 1 " clk $end
$var reg 1 # in $end
$var reg 1 $ reset $end
$scope module uut $end
$var wire 1 " clk $end
$var wire 1 # in $end
$var wire 1 $ reset $end
$var parameter 5 % A $end
$var parameter 5 & E $end
$var parameter 5 ' H $end
$var parameter 5 ( I $end
$var parameter 5 ) IDLE $end
$var parameter 5 * S $end
$var parameter 5 + T $end
$var parameter 5 , U $end
$var parameter 5 - V $end
$var reg 6 . next_state [5:0] $end
$var reg 8 / out [7:0] $end
$var reg 6 0 state [5:0] $end
$upscope $end
$upscope $end
$enddefinitions $end
$comment Show the parameter values. $end
$dumpall
b1110 -
b110 ,
b10 +
b111 *
bx )
b100 (
b1111 '
b0 &
b1 %
$end
#0
$dumpvars
bx 0
bx /
bx .
1$
x#
0"
bx !
$end
#100
b0 !
b0 /
b10 .
b0xxxxx 0
1"
#150
b0 .
1#
0$
#200
0"
#300
b1000101 !
b1000101 /
b100 .
b0 0
1"
#400
0"
#500
b1001001 !
b1001001 /
b111 .
b100 0
1"
#600
0"
#700
b1010011 !
b1010011 /
b1111 .
b111 0
1"
#750
1$
#800
0"
#900
b0 !
b0 /
b0 .
b0xxxxx 0
1"
#1000
0"
#1100
1"
#1200
0"
0$
#1300
b1000101 !
b1000101 /
b100 .
b0 0
1"
#1400
b1 .
0"
0#
#1500
b1000001 !
b1000001 /
b0xxxxx .
b1 0
1"
#1600
0"
1$
#1700
b0 !
b0 /
b10 .
b0xxxxx 0
1"
#1800
0"
#1900
1"
#2000
0"
#2050
b0 .
1#
0$
#2100
b1000101 !
b1000101 /
b100 .
b0 0
1"
#2200
0"
#2300
b1001001 !
b1001001 /
b111 .
b100 0
1"
#2400
0"
#2450
b110 .
0#
#2500
b1010101 !
b1010101 /
b0xxxxx .
b110 0
1"
#2600
0"
#2650
1$
#2700
b0 !
b0 /
b10 .
b0xxxxx 0
1"
#2800
0"
#2900
1"
#3000
0"
#3100
b1000101 !
b1000101 /
b0 0
b100 .
1"
1#
0$
#3200
0"
#3300
b1001001 !
b1001001 /
b111 .
b100 0
1"
#3400
0"
#3500
b1010011 !
b1010011 /
b1111 .
b111 0
1"
#3600
0"
#3700
b1010110 !
b1010110 /
b1110 0
b0xxxxx .
1"
0#
#3800
0"
#3900
b0 !
b0 /
b10 .
b0xxxxx 0
1"
1$
#4000
0"
#4100
1"
#4200
0"
#4300
1"
#4350
b0 .
1#
0$
#4400
0"
#4500
b1000101 !
b1000101 /
b100 .
b0 0
1"
