AP 6 - CD/contador assincrono/ff_jk.v
module ff_jk (j, k, pr, clr, clk , q);

    input j, k, pr, clr, clk;
    output reg q;

    always @ (negedge clk or negedge clr) begin
        if (pr == 0 & clr == 1) 
            q = 1;

        else if (pr == 1 & clr == 0)
            q = 0;

        else case ({j, k})
            2'b01: q = 0;
            2'b10: q = 1;
            2'b11: q = ~q;
            default: q = q;

        endcase;

    end

endmodule

AP 6 - CD/contador assincrono/contador-as.v
`include "ff_jk.v"

module contadoras(PR, CLR, Q, clk);
    
    output [3:0]Q;
    input PR, CLR;
    input clk;

    ff_jk uut(1'b1, 1'b1, PR, CLR, clk, Q[0]);
    ff_jk uut1(1'b1, 1'b1, PR, CLR, Q[0], Q[1]);
    ff_jk uut2(1'b1, 1'b1, PR, CLR, Q[1], Q[2]);
    ff_jk uut3(1'b1, 1'b1, PR, CLR, Q[2], Q[3]);

endmodule

AP 6 - CD/contador assincrono/contador-as_tb.v
`timescale 1ns/1ns
`include "contador-as.v"

module contadoras_tb;

   
    wire [3:0]Q;
    reg PR, CLR;
    reg clk;
    contadoras uut(PR, CLR, Q, clk);

    initial begin
        $dumpfile("contador-as.vcd");
        $dumpvars(0, contadoras_tb);

        PR = 1; CLR = 0; #15;
        PR = 1; CLR = 1; #320;
        
        $display("Teste completo");
        $finish;
    end

    initial begin
        clk = 0;
        forever #10 clk = ~clk;
    end

endmodule

AP 6 - CD/contador assincrono/contador-as.vcd
$date
	Fri Oct 25 09:41:48 2024
$end
$version
	Icarus Verilog
$end
$timescale
	1ns
$end
$scope module contadoras_tb $end
$var wire 4 ! Q [3:0] $end
$var reg 1 " CLR $end
$var reg 1 # PR $end
$var reg 1 $ clk $end
$scope module uut $end
$var wire 1 " CLR $end
$var wire 1 # PR $end
$var wire 1 $ clk $end
$var wire 4 % Q [3:0] $end
$scope module uut $end
$var wire 1 $ clk $end
$var wire 1 " clr $end
$var wire 1 & j $end
$var wire 1 ' k $end
$var wire 1 # pr $end
$var reg 1 ( q $end
$upscope $end
$scope module uut1 $end
$var wire 1 ) clk $end
$var wire 1 " clr $end
$var wire 1 * j $end
$var wire 1 + k $end
$var wire 1 # pr $end
$var reg 1 , q $end
$upscope $end
$scope module uut2 $end
$var wire 1 - clk $end
$var wire 1 " clr $end
$var wire 1 . j $end
$var wire 1 / k $end
$var wire 1 # pr $end
$var reg 1 0 q $end
$upscope $end
$scope module uut3 $end
$var wire 1 1 clk $end
$var wire 1 " clr $end
$var wire 1 2 j $end
$var wire 1 3 k $end
$var wire 1 # pr $end
$var reg 1 4 q $end
$upscope $end
$upscope $end
$upscope $end
$enddefinitions $end
$comment Show the parameter values. $end
$dumpall
$end
#0
$dumpvars
04
13
12
01
00
1/
1.
0-
0,
1+
1*
0)
0(
1'
1&
b0 %
0$
1#
0"
b0 !
$end
#10
1$
#15
1"
#20
1)
b1 !
b1 %
1(
0$
#30
1$
#40
1-
1,
0)
b10 !
b10 %
0(
0$
#50
1$
#60
1)
b11 !
b11 %
1(
0$
#70
1$
#80
11
10
0-
0,
0)
b100 !
b100 %
0(
0$
#90
1$
#100
1)
b101 !
b101 %
1(
0$
#110
1$
#120
1-
1,
0)
b110 !
b110 %
0(
0$
#130
1$
#140
1)
b111 !
b111 %
1(
0$
#150
1$
#160
14
01
00
0-
0,
0)
b1000 !
b1000 %
0(
0$
#170
1$
#180
1)
b1001 !
b1001 %
1(
0$
#190
1$
#200
1-
1,
0)
b1010 !
b1010 %
0(
0$
#210
1$
#220
1)
b1011 !
b1011 %
1(
0$
#230
1$
#240
11
10
0-
0,
0)
b1100 !
b1100 %
0(
0$
#250
1$
#260
1)
b1101 !
b1101 %
1(
0$
#270
1$
#280
1-
1,
0)
b1110 !
b1110 %
0(
0$
#290
1$
#300
1)
b1111 !
b1111 %
1(
0$
#310
1$
#320
04
01
00
0-
0,
0)
b0 !
b0 %
0(
0$
