AP3 - CD/Encoder/codificador.v
module codificador (bcd, l);

input [3:0]bcd;
output reg [6:0]l;

always @ (bcd) begin
    case(bcd)
        4'b0000: l = 7'b1111110; //0
        4'b0001: l = 7'b0110000; //1
        4'b0010: l = 7'b1101101; //2
        4'b0011: l = 7'b1110001; //3
        4'b0100: l = 7'b0110011; //4
        4'b0101: l = 7'b1011011; //5
        4'b0110: l = 7'b1011111; //6
        4'b0111: l = 7'b1110000; //7
        4'b1000: l = 7'b1111111; //8
        4'b1001: l = 7'b1111011; //9
        4'b0110: l = 7'b1110111; //A
        4'b0110: l = 7'b0011111; //b
        4'b0110: l = 7'b0001101; //c
        4'b0110: l = 7'b1001111; //e
        4'b0110: l = 7'b1000111; //f
        default: l = 7'b0000000;
    endcase;
end
endmodule

AP3 - CD/Encoder/codificador_tb.v
`timescale 1ns/1ns
`include "codificador.v"

module codificador_tb;

    reg [3:0]bcd;
    wire [6:0]l;
    codificador uut(bcd, l);

    initial begin
        $dumpfile("codificador_tb.vcd");
        $dumpvars(1);
        bcd = 4'b0000; #20;
        bcd = 4'b0001; #20;
        bcd = 4'b0010; #20;
        bcd = 4'b0011; #20;
        bcd = 4'b0100; #20;
        bcd = 4'b0101; #20;
        bcd = 4'b0110; #20;
        bcd = 4'b0111; #20;
        bcd = 4'b1000; #20;
        bcd = 4'b1001; #20;
        bcd = 4'b0110; #20;
        bcd = 4'b0110; #20;
        bcd = 4'b0110; #20;
        bcd = 4'b0110; #20;
        bcd = 4'b0110; #20;

        $display("Teste completo");
    end

endmodule

AP3 - CD/Encoder/codificador_tb.vcd
$date
	Fri Sep 20 09:00:08 2024
$end
$version
	Icarus Verilog
$end
$timescale
	1ns
$end
$scope module codificador_tb $end
$var wire 7 ! l [6:0] $end
$var reg 4 " bcd [3:0] $end
$upscope $end
$enddefinitions $end
$comment Show the parameter values. $end
$dumpall
$end
#0
$dumpvars
b0 "
b1111110 !
$end
#20
b110000 !
b1 "
#40
b1101101 !
b10 "
#60
b1110001 !
b11 "
#80
b110011 !
b100 "
#100
b1011011 !
b101 "
#120
b1011111 !
b110 "
#140
b1110000 !
b111 "
#160
b1111111 !
b1000 "
#180
b1111011 !
b1001 "
#200
b1011111 !
b110 "
