AP3 - CD/Decoder/decodificador.v
module decodificador (a, en, d);

    input [2:0]a;
    input en;
    output reg [7:0]d;

    always @ (a or en) begin
        if (en == 1'b1) begin 
            case(a)
                3'b000: d = 8'b00000001; //d0
                3'b001: d = 8'b00000010; //d1
                3'b010: d = 8'b00000100; //d2
                3'b011: d = 8'b00001000; //d3
                3'b100: d = 8'b00010000; //d4
                3'b101: d = 8'b00100000; //d5
                3'b110: d = 8'b01000000; //d6
                3'b111: d = 8'b10000000; //d7
            default: d = 8'b00000000;
            endcase;
        end
        else
        d = 8'b00000000;
    end

endmodule

AP3 - CD/Decoder/decodificador_tb.v
`timescale 1ns/1ns
`include "decodificador.v"

module decodificador_tb;

    reg [2:0]a;
    reg en;
    wire [7:0]d;
    decodificador uut(a, en, d);

    initial begin
        $dumpfile("decodificador_tb.vcd");
        $dumpvars(1);
        en = 1'b1;
        a = 4'b000; #20;
        a = 4'b001; #20;
        a = 4'b010; #20;
        a = 4'b011; #20;
        a = 4'b100; #20;
        a = 4'b101; #20;
        a = 4'b110; #20;
        a = 4'b111; #20;
        en = 1'b0; #20;

        $display("Teste completo");
    end

endmodule

AP3 - CD/Decoder/decodificador_tb.vcd
$date
	Fri Sep 20 09:45:34 2024
$end
$version
	Icarus Verilog
$end
$timescale
	1ns
$end
$scope module decodificador_tb $end
$var wire 8 ! d [7:0] $end
$var reg 3 " a [2:0] $end
$var reg 1 # en $end
$upscope $end
$enddefinitions $end
$comment Show the parameter values. $end
$dumpall
$end
#0
$dumpvars
1#
b0 "
b1 !
$end
#20
b10 !
b1 "
#40
b100 !
b10 "
#60
b1000 !
b11 "
#80
b10000 !
b100 "
#100
b100000 !
b101 "
#120
b1000000 !
b110 "
#140
b10000000 !
b111 "
#160
b0 !
0#
