AP1 - CD/ex3.v
module alarme (p, w, m, s, a);

    input p, w, m, s;
    output a;

    assign a = p & s | w & s | m;

endmodule

AP1 - CD/alarme_tb.v
`timescale 1ns/1ns
`include "ex3.v"

module alarme_tb;

    reg P, W, M, S;
    wire A;
    alarme uut(P, W, M, S, A);

    initial begin
        $dumpfile("alarme_tb.vcd");
        $dumpvars(0, alarme_tb);

        P = 0; W = 0; M = 0; S = 0; #20;
        P = 0; W = 0; M = 0; S = 1; #20;
        P = 0; W = 0; M = 1; S = 0; #20;
        P = 0; W = 0; M = 1; S = 1; #20;
        P = 0; W = 1; M = 0; S = 0; #20;
        P = 0; W = 1; M = 0; S = 1; #20;
        P = 0; W = 1; M = 1; S = 0; #20;
        P = 0; W = 1; M = 1; S = 1; #20;
        P = 1; W = 0; M = 0; S = 0; #20;
        P = 1; W = 0; M = 0; S = 1; #20;
        P = 1; W = 0; M = 1; S = 0; #20;
        P = 1; W = 0; M = 1; S = 1; #20;
        P = 1; W = 1; M = 0; S = 0; #20;
        P = 1; W = 1; M = 0; S = 1; #20;
        P = 1; W = 1; M = 1; S = 0; #20;
        P = 1; W = 1; M = 1; S = 1; #20;



        $display("Teste completo");
    end

endmodule

AP1 - CD/alarme_tb.vcd
$date
	Fri Sep 06 09:58:06 2024
$end
$version
	Icarus Verilog
$end
$timescale
	1ns
$end
$scope module alarme_tb $end
$var wire 1 ! A $end
$var reg 1 " M $end
$var reg 1 # P $end
$var reg 1 $ S $end
$var reg 1 % W $end
$scope module uut $end
$var wire 1 ! a $end
$var wire 1 " m $end
$var wire 1 # p $end
$var wire 1 $ s $end
$var wire 1 % w $end
$upscope $end
$upscope $end
$enddefinitions $end
$comment Show the parameter values. $end
$dumpall
$end
#0
$dumpvars
0%
0$
0#
0"
0!
$end
#20
1$
#40
1!
0$
1"
#60
1$
#80
0!
0$
0"
1%
#100
1!
1$
#120
0$
1"
#140
1$
#160
0!
0$
0"
0%
1#
#180
1!
1$
#200
0$
1"
#220
1$
#240
0!
0$
0"
1%
#260
1!
1$
#280
0$
1"
#300
1$
