AP4 - CD/full_subtractor/full_subtractor.v
module full_subtractor(a, b, s, c1, c2);

    input a, b, c1;
    output s, c2;

    assign s = a ^ b ^ c1;
    assign c2 = (~a & b) + (~a & c1) + (b & c1);

endmodule

AP4 - CD/full_subtractor/full_subtractor_tb.v
`timescale 1ns/1ns
`include "full_subtractor.v"

module full_subtractor_tb;

    reg a, b, c1;
    wire s, c2;
    full_subtractor uut(a, b, s, c1, c2);

    initial begin
        $dumpfile("full_subtractor_tb.vcd");
        $dumpvars(0, full_subtractor_tb);
        a = 1'b0; b = 1'b0; c1 = 1'b0; #20;
        a = 1'b0; b = 1'b0; c1 = 1'b1; #20;
        a = 1'b0; b = 1'b1; c1 = 1'b0; #20;
        a = 1'b0; b = 1'b1; c1 = 1'b1; #20;
        a = 1'b1; b = 1'b0; c1 = 1'b0; #20;
        a = 1'b1; b = 1'b0; c1 = 1'b1; #20;
        a = 1'b1; b = 1'b1; c1 = 1'b0; #20;
        a = 1'b1; b = 1'b1; c1 = 1'b1; #20;

        
        $display("Teste completo");
    end

endmodule

AP4 - CD/full_subtractor/full_subtractor_tb.vcd
$date
	Fri Sep 27 09:13:14 2024
$end
$version
	Icarus Verilog
$end
$timescale
	1ns
$end
$scope module full_subtractor_tb $end
$var wire 1 ! s $end
$var wire 1 " c2 $end
$var reg 1 # a $end
$var reg 1 $ b $end
$var reg 1 % c1 $end
$scope module uut $end
$var wire 1 # a $end
$var wire 1 $ b $end
$var wire 1 % c1 $end
$var wire 1 ! s $end
$var wire 1 " c2 $end
$upscope $end
$upscope $end
$enddefinitions $end
$comment Show the parameter values. $end
$dumpall
$end
#0
$dumpvars
0%
0$
0#
0"
0!
$end
#20
1!
1"
1%
#40
1"
0%
1$
#60
0!
1"
1%
#80
1!
0"
0%
0$
1#
#100
0!
1%
#120
0%
1$
#140
1!
1"
1%
