AP4 - CD/full_adder/full_adder.v
module full_adder(a, b, s, c1, c2);

    input a, b, c1;
    output s, c2;

    assign s = a ^ b ^ c1;
    assign c2 = (b & c1) + (a & c1) + (a & b);

endmodule

AP4 - CD/full_adder/full_adder_tb.v
`timescale 1ns/1ns
`include "full_adder.v"

module full_adder_tb;

    reg a, b, c1;
    wire s, c2;
    full_adder uut(a, b, s, c1, c2);

    initial begin
        $dumpfile("full_adder_tb.vcd");
        $dumpvars(0, full_adder_tb);
        a = 1'b0; b = 1'b0; c1 = 1'b0; #20;
        a = 1'b0; b = 1'b0; c1 = 1'b1; #20;
        a = 1'b0; b = 1'b1; c1 = 1'b0; #20;
        a = 1'b0; b = 1'b1; c1 = 1'b1; #20;
        a = 1'b1; b = 1'b0; c1 = 1'b0; #20;
        a = 1'b1; b = 1'b0; c1 = 1'b1; #20;
        a = 1'b1; b = 1'b1; c1 = 1'b0; #20;
        a = 1'b1; b = 1'b1; c1 = 1'b1; #20;

        
        $display("Teste completo");
    end

endmodule

AP4 - CD/full_adder/full_adder_tb.vcd
$date
	Fri Sep 27 08:51:27 2024
$end
$version
	Icarus Verilog
$end
$timescale
	1ns
$end
$scope module full_adder_tb $end
$var wire 1 ! s $end
$var wire 1 " c2 $end
$var reg 1 # a $end
$var reg 1 $ b $end
$var reg 1 % c1 $end
$scope module uut $end
$var wire 1 # a $end
$var wire 1 $ b $end
$var wire 1 % c1 $end
$var wire 1 ! s $end
$var wire 1 " c2 $end
$upscope $end
$upscope $end
$enddefinitions $end
$comment Show the parameter values. $end
$dumpall
$end
#0
$dumpvars
0%
0$
0#
0"
0!
$end
#20
1!
1%
#40
0%
1$
#60
0!
1"
1%
#80
1!
0"
0%
0$
1#
#100
0!
1"
1%
#120
1"
0%
1$
#140
1!
1"
1%
