AP5 - CD/ff_jk/ff_jk.v
module ff_jk (j, k, pr, clr, clk , q);

    input j, k, pr, clr, clk;
    output reg q;

    always @ (posedge clk) begin
        if (pr == 0 & clr == 1) 
            q = 1;

        else if (pr == 1 & clr == 0)
            q = 0;

        else case ({j, k})
            2'b01: q = 0;
            2'b10: q = 1;
            2'b11: q = ~q;

        default: q = q;

        endcase;

    end

endmodule

AP5 - CD/ff_jk/ff_jk_tb.v
`timescale 1ns/1ns
`include "ff_jk.v"

module ff_jk_tb;

    reg j, k, pr, clr, clk;
    wire q;
    ff_jk uut(j, k, pr, clr, clk, q);

    initial begin
    $dumpfile ("ff_jk_tb.vcd");
    $dumpvars (1);

            pr = 1; clr = 0; #20;
            pr = 1; clr = 1; j = 0; k = 0; #20;
            j = 0; k = 1; #20;
            j = 1; k = 0; #20;
            j = 1; k = 1; #20;
            $finish;
        end

    initial begin
        clk = 0;
        forever #10 clk = ~ clk;
    end
    endmodule

AP5 - CD/ff_jk/ff_jk_tb.vcd
$date
	Fri Oct 04 08:58:09 2024
$end
$version
	Icarus Verilog
$end
$timescale
	1ns
$end
$scope module ff_jk_tb $end
$var wire 1 ! q $end
$var reg 1 " clk $end
$var reg 1 # clr $end
$var reg 1 $ j $end
$var reg 1 % k $end
$var reg 1 & pr $end
$upscope $end
$enddefinitions $end
$comment Show the parameter values. $end
$dumpall
$end
#0
$dumpvars
1&
x%
x$
0#
0"
x!
$end
#10
0!
1"
#20
0"
0%
0$
1#
#30
1"
#40
0"
1%
#50
1"
#60
0"
0%
1$
#70
1!
1"
#80
0"
1%
#90
0!
1"
